.git_archival.txt
.gitattributes
.gitignore
.pre-commit-config.yaml
.readthedocs.yaml
CHANGELOG.md
CONTRIBUTING.md
LICENSE
README.md
build.py
main.py
noxfile.py
pyproject.toml
requirements-dev.txt
requirements-proxy.txt
requirements.txt
.devcontainer/devcontainer.json
.github/CONTRIBUTING.md
.github/dependabot.yml
.github/release.yml
.github/workflows/cd.yml
.github/workflows/ci.yml
collector/collector-config.yaml
docs/conf.py
docs/index.md
examples/test_scipy.ipynb
examples/test_scipy.py
examples/test_span.py
examples/test_stats_uploader.py
examples/test_statswrapper.py
src/telemetric/__init__.py
src/telemetric/_version.py
src/telemetric/_version.pyi
src/telemetric/console.py
src/telemetric/path_finder.py
src/telemetric/py.typed
src/telemetric/span.py
src/telemetric.egg-info/PKG-INFO
src/telemetric.egg-info/SOURCES.txt
src/telemetric.egg-info/dependency_links.txt
src/telemetric.egg-info/top_level.txt
src/telemetric/ga4/__init__.py
src/telemetric/ga4/analytics.py
src/telemetric/ga4/ga4_proxy.py
src/telemetric/ga4/stats_uploader.py
src/telemetric/statswrapper/__init__.py
src/telemetric/statswrapper/_stats_wrapper.c
tests/test_package.py
tests/collector/collector-config.yaml