Metadata-Version: 2.4
Name: telemetric
Version: 0.0.1rc1
Summary: API tracer to gather usage telemetry for Python libraries
Author-email: Guen Prawiroatmodjo <4041805+guenp@users.noreply.github.com>, Sebastian Berg <sebastian@sipsolutions.net>
License-Expression: BSD-3-Clause
Project-URL: Homepage, https://github.com/scientific-python/telemetric
Project-URL: Bug Tracker, https://github.com/scientific-python/telemetric/issues
Project-URL: Discussions, https://github.com/scientific-python/telemetric/discussions
Project-URL: Changelog, https://github.com/scientific-python/telemetric/releases
Classifier: Development Status :: 1 - Planning
Classifier: Intended Audience :: Science/Research
Classifier: Intended Audience :: Developers
Classifier: Operating System :: OS Independent
Classifier: Programming Language :: Python
Classifier: Programming Language :: Python :: 3
Classifier: Programming Language :: Python :: 3 :: Only
Classifier: Programming Language :: Python :: 3.9
Classifier: Programming Language :: Python :: 3.10
Classifier: Programming Language :: Python :: 3.11
Classifier: Programming Language :: Python :: 3.12
Classifier: Programming Language :: Python :: 3.13
Classifier: Topic :: Scientific/Engineering
Classifier: Typing :: Typed
Requires-Python: >=3.9
License-File: LICENSE
Dynamic: license-file
